tempest/__init__.py
tempest/cluster.py
tempest/config.py
tempest/core.py
tempest/mcmc.py
tempest/modes.py
tempest/sampler.py
tempest/state_manager.py
tempest/student.py
tempest/tools.py
tempest/steps/__init__.py
tempest/steps/mutate.py
tempest/steps/resample.py
tempest/steps/reweight.py
tempest/steps/train.py
tempest_sampler-0.1.5.dist-info/licenses/LICENCE
tempest_sampler-0.1.5.dist-info/METADATA
tempest_sampler-0.1.5.dist-info/WHEEL
tempest_sampler-0.1.5.dist-info/top_level.txt
tempest_sampler-0.1.5.dist-info/RECORD
