Metadata-Version: 2.4
Name: tempest-sampler
Version: 0.1.5
Summary: Persistent Sampling
Author-email: Minas Karamanis <minaskar@gmail.com>
License: MIT
Project-URL: Homepage, https://github.com/minaskar/tempest
Classifier: Programming Language :: Python :: 3
Classifier: License :: OSI Approved :: MIT License
Classifier: Operating System :: OS Independent
Classifier: Intended Audience :: Science/Research
Classifier: Topic :: Scientific/Engineering
Classifier: Topic :: Scientific/Engineering :: Mathematics
Requires-Python: >=3.8
License-File: LICENCE
Requires-Dist: numpy>=1.20.0
Requires-Dist: tqdm>=4.60.0
Requires-Dist: scipy>=1.4.0
Requires-Dist: dill>=0.3.8
Requires-Dist: multiprocess>=0.70.15
Requires-Dist: matplotlib>=3.7.5
Requires-Dist: corner>=2.2.1
Dynamic: license-file
